{"id":4970,"global_id":"www.unitingnc.org?id=4970","global_id_lineage":["www.unitingnc.org?id=4970"],"author":"25","status":"publish","date":"2019-05-16 11:44:33","date_utc":"2019-05-16 15:44:33","modified":"2019-05-16 11:44:33","modified_utc":"2019-05-16 15:44:33","url":"https:\/\/www.unitingnc.org\/stand-with-us\/may-18-letter-delivery-at-the-governors-mansion-raleigh\/","rest_url":"https:\/\/www.unitingnc.org\/wp-json\/tribe\/events\/v1\/events\/4970","title":"May 18: Letter Delivery at the Governors Mansion (Raleigh)","description":"<p>Espa\u00f1ol abajo:<\/p>\n<p>HB370 is a &#8220;Show me your papers&#8221; bill that would require NC Sheriffs to collaborate with ICE. Immigrant rights groups across the state are joining in arms to fight back against this retaliatory bill that wishes to punish counties whose sheriffs terminated their relationship with ICE.<\/p>\n<p>Join us at the Governors Mansion in Raleigh as we rally to deliver letters from community members demanding that Governor Cooper veto HB 370 or any other copycat bill if it lands on his desk.<\/p>\n<p>&#8212;<br \/>\nLa HB370 una propuesta anti-migratoria requiere que los alguaciles del estado colaboran con ICE. Grupos de los derechos de los inmigrantes est\u00e1n trabajando juntos para detener esta propuesta que busca castigar a los condados cuales alguaciles terminaron su relaci\u00f3n con ICE.<\/p>\n<p>Acomp\u00e1\u00f1enos a la mansi\u00f3n del gobernador en Raleigh para entregar cartas de miembros comunitarios que demandan que el Gobernador Cooper utilice su poder del veto si la HB 370 o otra propuesta similar llegue en su escritorio!<\/p>","excerpt":"<a href=\"\" class=\"more-link\" title=\"Read More\">Read More<\/a>","slug":"may-18-letter-delivery-at-the-governors-mansion-raleigh","image":{"url":"https:\/\/www.unitingnc.org\/wp-content\/uploads\/2019\/05\/60209841_815611358811496_2455286572371673088_n.png","id":4972,"extension":"png","width":775,"height":403,"sizes":{"thumbnail":{"width":150,"height":150,"mime-type":"image\/png","url":"https:\/\/www.unitingnc.org\/wp-content\/uploads\/2019\/05\/60209841_815611358811496_2455286572371673088_n-150x150.png"},"medium":{"width":300,"height":156,"mime-type":"image\/png","url":"https:\/\/www.unitingnc.org\/wp-content\/uploads\/2019\/05\/60209841_815611358811496_2455286572371673088_n-300x156.png"},"medium_large":{"width":768,"height":399,"mime-type":"image\/png","url":"https:\/\/www.unitingnc.org\/wp-content\/uploads\/2019\/05\/60209841_815611358811496_2455286572371673088_n-768x399.png"},"home-bottom":{"width":150,"height":150,"mime-type":"image\/png","url":"https:\/\/www.unitingnc.org\/wp-content\/uploads\/2019\/05\/60209841_815611358811496_2455286572371673088_n-150x150.png"},"home-middle":{"width":332,"height":190,"mime-type":"image\/png","url":"https:\/\/www.unitingnc.org\/wp-content\/uploads\/2019\/05\/60209841_815611358811496_2455286572371673088_n-332x190.png"},"home-top":{"width":700,"height":400,"mime-type":"image\/png","url":"https:\/\/www.unitingnc.org\/wp-content\/uploads\/2019\/05\/60209841_815611358811496_2455286572371673088_n-700x400.png"},"slider":{"width":775,"height":400,"mime-type":"image\/png","url":"https:\/\/www.unitingnc.org\/wp-content\/uploads\/2019\/05\/60209841_815611358811496_2455286572371673088_n-775x400.png"},"woocommerce_thumbnail":{"width":450,"height":403,"mime-type":"image\/png","uncropped":false,"url":"https:\/\/www.unitingnc.org\/wp-content\/uploads\/2019\/05\/60209841_815611358811496_2455286572371673088_n-450x403.png"},"woocommerce_single":{"width":725,"height":377,"mime-type":"image\/png","url":"https:\/\/www.unitingnc.org\/wp-content\/uploads\/2019\/05\/60209841_815611358811496_2455286572371673088_n-725x377.png"},"woocommerce_gallery_thumbnail":{"width":100,"height":100,"mime-type":"image\/png","url":"https:\/\/www.unitingnc.org\/wp-content\/uploads\/2019\/05\/60209841_815611358811496_2455286572371673088_n-100x100.png"},"shop_catalog":{"width":450,"height":403,"mime-type":"image\/png","url":"https:\/\/www.unitingnc.org\/wp-content\/uploads\/2019\/05\/60209841_815611358811496_2455286572371673088_n-450x403.png"},"shop_single":{"width":725,"height":377,"mime-type":"image\/png","url":"https:\/\/www.unitingnc.org\/wp-content\/uploads\/2019\/05\/60209841_815611358811496_2455286572371673088_n-725x377.png"},"shop_thumbnail":{"width":100,"height":100,"mime-type":"image\/png","url":"https:\/\/www.unitingnc.org\/wp-content\/uploads\/2019\/05\/60209841_815611358811496_2455286572371673088_n-100x100.png"}}},"all_day":false,"start_date":"2019-05-18 14:00:00","start_date_details":{"year":"2019","month":"05","day":"18","hour":"14","minutes":"00","seconds":"00"},"end_date":"2019-05-18 15:30:00","end_date_details":{"year":"2019","month":"05","day":"18","hour":"15","minutes":"30","seconds":"00"},"utc_start_date":"2019-05-18 18:00:00","utc_start_date_details":{"year":"2019","month":"05","day":"18","hour":"18","minutes":"00","seconds":"00"},"utc_end_date":"2019-05-18 19:30:00","utc_end_date_details":{"year":"2019","month":"05","day":"18","hour":"19","minutes":"30","seconds":"00"},"timezone":"America\/New_York","timezone_abbr":"EDT","cost":"","cost_details":{"currency_symbol":"","currency_position":"prefix","values":[]},"website":"","show_map":true,"show_map_link":true,"hide_from_listings":false,"sticky":false,"featured":false,"categories":[],"tags":[],"venue":{"id":4976,"author":"25","status":"publish","date":"2019-05-16 11:44:33","date_utc":"2019-05-16 15:44:33","modified":"2019-05-16 11:44:33","modified_utc":"2019-05-16 15:44:33","url":"https:\/\/www.unitingnc.org\/venue\/200-n-blount-st-3\/","venue":"200 N Blount St","excerpt":"<a href=\"\" class=\"more-link\" title=\"Read More\">Read More<\/a>","slug":"200-n-blount-st-3","address":"200 N Blount St","city":"Raleigh","province":"NC","zip":"27601-1006","stateprovince":"NC","geo_lat":35.7831598,"geo_lng":-78.6355424,"json_ld":{"@type":"Place","name":"200 N Blount St","description":"","url":"https:\/\/www.unitingnc.org\/venue\/200-n-blount-st-3\/","address":{"@type":"PostalAddress","streetAddress":"200 N Blount St","addressLocality":"Raleigh","addressRegion":"NC","postalCode":"27601-1006"},"geo":{"@type":"GeoCoordinates","latitude":35.7831598,"longitude":-78.6355424},"telephone":"","sameAs":""},"show_map":true,"show_map_link":true,"global_id":"www.unitingnc.org?id=4976","global_id_lineage":["www.unitingnc.org?id=4976"]},"organizer":[],"json_ld":{"@context":"http:\/\/schema.org","@type":"Event","name":"May 18: Letter Delivery at the Governors Mansion (Raleigh)","description":"&lt;p&gt;Espa\u00f1ol abajo: HB370 is a &quot;Show me your papers&quot; bill that would require NC Sheriffs to collaborate with ICE. Immigrant rights groups across the state are joining in arms to fight back against this retaliatory bill that wishes to punish counties whose sheriffs terminated their relationship with ICE. Join us at the Governors Mansion in [&hellip;]&lt;\/p&gt;\\n","image":"https:\/\/www.unitingnc.org\/wp-content\/uploads\/2019\/05\/60209841_815611358811496_2455286572371673088_n.png","url":"https:\/\/www.unitingnc.org\/stand-with-us\/may-18-letter-delivery-at-the-governors-mansion-raleigh\/","startDate":"2019-05-18T14:00:00-04:00","endDate":"2019-05-18T15:30:00-04:00","location":{"@type":"Place","name":"200 N Blount St","description":"","url":"https:\/\/www.unitingnc.org\/venue\/200-n-blount-st-3\/","address":{"@type":"PostalAddress","streetAddress":"200 N Blount St","addressLocality":"Raleigh","addressRegion":"NC","postalCode":"27601-1006"},"geo":{"@type":"GeoCoordinates","latitude":35.7831598,"longitude":-78.6355424},"telephone":"","sameAs":""},"performer":"Organization"}}