{"id":2814,"global_id":"www.unitingnc.org?id=2814","global_id_lineage":["www.unitingnc.org?id=2814"],"author":"10","status":"publish","date":"2017-03-23 11:59:33","date_utc":"2017-03-23 15:59:33","modified":"2017-03-23 11:59:33","modified_utc":"2017-03-23 15:59:33","url":"https:\/\/www.unitingnc.org\/stand-with-us\/march-18-legal-forum-foro-legal-siler-city\/","rest_url":"https:\/\/www.unitingnc.org\/wp-json\/tribe\/events\/v1\/events\/2814","title":"March 18: Legal Forum \/ Foro Legal (Siler City)","description":"<p>(English below) AP\u00daNTESE PARA RESERVAR SU ASIENTO. Inscripci\u00f3n a las 8:30 AM, el programa empieza a las 9:30. Hablaremos sobre: Conozca sus derechos. Plan de emergencia para familias (cartas poderes); Di\u00e1logo con Agentes de la Ley de Chatham; Actualizaci\u00f3n de las \u00f3rdenes ejecutivas; Leyes de NC que impactan a los inmigrantes, \u00a1y m\u00e1s! Gratis! Mesas informativas de abogados y agencias, musica en vivo y se puede comprar su almuerzo en el evento.<\/p>\n<p>SIGN UP TO RESERVE YOUR SEAT. The Legal Fair is an all-day event. Registration starts at 8:30AM, and the program at 9:30 AM. Workshops about: Know your rights; Emergency family planning (powers of attorney); Dialog with Chatham; Law Enforcement officials; Update on executive orders; NC laws that impact immigrants; and more! Information tables from attorneys and non-profit agencies. Live music and other entertainment during lunch. Free! Lunch will be for sale at the event.<\/p>","excerpt":"<a href=\"\" class=\"more-link\" title=\"Read More\">Read More<\/a>","slug":"march-18-legal-forum-foro-legal-siler-city","image":false,"all_day":false,"start_date":"2017-03-18 09:00:00","start_date_details":{"year":"2017","month":"03","day":"18","hour":"09","minutes":"00","seconds":"00"},"end_date":"2017-03-18 17:30:00","end_date_details":{"year":"2017","month":"03","day":"18","hour":"17","minutes":"30","seconds":"00"},"utc_start_date":"2017-03-18 13:00:00","utc_start_date_details":{"year":"2017","month":"03","day":"18","hour":"13","minutes":"00","seconds":"00"},"utc_end_date":"2017-03-18 21:30:00","utc_end_date_details":{"year":"2017","month":"03","day":"18","hour":"21","minutes":"30","seconds":"00"},"timezone":"America\/New_York","timezone_abbr":"EDT","cost":"","cost_details":{"currency_symbol":"","currency_position":"prefix","values":[]},"website":"","show_map":true,"show_map_link":true,"hide_from_listings":false,"sticky":false,"featured":false,"categories":[],"tags":[],"venue":{"id":2815,"author":"10","status":"publish","date":"2017-03-23 11:59:33","date_utc":"2017-03-23 15:59:33","modified":"2017-03-23 11:59:33","modified_utc":"2017-03-23 15:59:33","url":"https:\/\/www.unitingnc.org\/venue\/siler-city\/","venue":"Siler City","excerpt":"<a href=\"\" class=\"more-link\" title=\"Read More\">Read More<\/a>","slug":"siler-city","address":"1334 E 11th St","city":"Siler City","country":"United States","state":"NC","zip":"27344","website":"https:\/\/www.facebook.com\/events\/104023160115295\/","stateprovince":"NC","geo_lat":35.7327676,"geo_lng":-79.4471576,"json_ld":{"@type":"Place","name":"Siler City","description":"","url":"https:\/\/www.unitingnc.org\/venue\/siler-city\/","address":{"@type":"PostalAddress","streetAddress":"1334 E 11th St","addressLocality":"Siler City","addressRegion":"NC","postalCode":"27344","addressCountry":"United States"},"geo":{"@type":"GeoCoordinates","latitude":35.7327676,"longitude":-79.4471576},"telephone":"","sameAs":"https:\/\/www.facebook.com\/events\/104023160115295\/"},"show_map":true,"show_map_link":true,"global_id":"www.unitingnc.org?id=2815","global_id_lineage":["www.unitingnc.org?id=2815"]},"organizer":[],"json_ld":{"@context":"http:\/\/schema.org","@type":"Event","name":"March 18: Legal Forum \/ Foro Legal (Siler City)","description":"&lt;p&gt;(English below) AP\u00daNTESE PARA RESERVAR SU ASIENTO. Inscripci\u00f3n a las 8:30 AM, el programa empieza a las 9:30. Hablaremos sobre: Conozca sus derechos. Plan de emergencia para familias (cartas poderes); Di\u00e1logo con Agentes de la Ley de Chatham; Actualizaci\u00f3n de las \u00f3rdenes ejecutivas; Leyes de NC que impactan a los inmigrantes, \u00a1y m\u00e1s! Gratis! Mesas [&hellip;]&lt;\/p&gt;\\n","url":"https:\/\/www.unitingnc.org\/stand-with-us\/march-18-legal-forum-foro-legal-siler-city\/","startDate":"2017-03-18T09:00:00-04:00","endDate":"2017-03-18T17:30:00-04:00","location":{"@type":"Place","name":"Siler City","description":"","url":"https:\/\/www.unitingnc.org\/venue\/siler-city\/","address":{"@type":"PostalAddress","streetAddress":"1334 E 11th St","addressLocality":"Siler City","addressRegion":"NC","postalCode":"27344","addressCountry":"United States"},"geo":{"@type":"GeoCoordinates","latitude":35.7327676,"longitude":-79.4471576},"telephone":"","sameAs":"https:\/\/www.facebook.com\/events\/104023160115295\/"},"performer":"Organization"}}